{"title":"健身运动","uid":"0670bb48035640620318bcdcbb65df82","slug":"lifehealth","date":"2018-05-21T06:00:14.000Z","updated":"2022-02-18T10:17:38.000Z","comments":true,"path":"api/articles/lifehealth.json","cover":[],"content":"<hr>\n<p>健身圈从来就是一个强者的舞台，有的人通过健身强健了体魄，有的人通过健身找到了自信。正所谓“一入健身深似海”，健身就是有这样的魔力让你欲罢不能。</p>\n<img src=\"/post/lifehealth/83b8000151b5571c9367.jpg\" class=\"\" title=\"img1\">\n\n<span id=\"more\"></span>\n<h1 id=\"深蹲跳\"><a href=\"#深蹲跳\" class=\"headerlink\" title=\"深蹲跳\"></a>深蹲跳</h1><hr>\n<p>锻炼部位：股四头肌、腘绳肌、臀大肌、腓肠肌。</p>\n<img src=\"/post/lifehealth/1.gif\" class=\"\" title=\"avatar\">\n\n<h1 id=\"俯卧撑\"><a href=\"#俯卧撑\" class=\"headerlink\" title=\"俯卧撑\"></a>俯卧撑</h1><hr>\n<p>锻炼部位：胸大肌、肱三头肌。</p>\n<img src=\"/post/lifehealth/2.gif\" class=\"\" title=\"avatar\">\n\n<h1 id=\"开合跳\"><a href=\"#开合跳\" class=\"headerlink\" title=\"开合跳\"></a>开合跳</h1><hr>\n<p>锻炼部位：股四头肌、三角肌、比目鱼肌、腓肠肌。</p>\n<img src=\"/post/lifehealth/3.gif\" class=\"\" title=\"avatar\">\n\n<h2 id=\"登山者\"><a href=\"#登山者\" class=\"headerlink\" title=\"登山者\"></a>登山者</h2><hr>\n<p>锻炼部位：股四头肌、腘绳肌、胸肌。</p>\n<img src=\"/post/lifehealth/4.gif\" class=\"\" title=\"avatar\">\n\n<h1 id=\"波比跳\"><a href=\"#波比跳\" class=\"headerlink\" title=\"波比跳\"></a>波比跳</h1><hr>\n<p>锻炼部位：股四头肌、三角肌、腹直肌。</p>\n<img src=\"/post/lifehealth/5.gif\" class=\"\" title=\"avatar\">\n\n\n\n<p>—贵在坚持—</p>\n","text":" 健身圈从来就是一个强者的舞台，有的人通过健身强健了体魄，有的人通过健身找到了自信。正所谓“一入健身深似海”，健身就是有这样的魔力让你欲罢不能。 深蹲跳 锻炼部位：股四头肌、腘绳肌、臀大肌、腓肠肌。 俯卧撑 锻炼部位：胸大肌、肱三头肌。 开合跳 锻炼部位：股四头肌、三角肌、比目鱼...","link":"","photos":[],"count_time":{"symbolsCount":214,"symbolsTime":"1 mins."},"categories":[{"name":"生活","slug":"生活","count":4,"path":"api/categories/生活.json"}],"tags":[{"name":"生活","slug":"生活","count":2,"path":"api/tags/生活.json"},{"name":"运动","slug":"运动","count":1,"path":"api/tags/运动.json"}],"toc":"<ol class=\"toc\"><li class=\"toc-item toc-level-1\"><a class=\"toc-link\" href=\"#%E6%B7%B1%E8%B9%B2%E8%B7%B3\"><span class=\"toc-text\">深蹲跳</span></a></li><li class=\"toc-item toc-level-1\"><a class=\"toc-link\" href=\"#%E4%BF%AF%E5%8D%A7%E6%92%91\"><span class=\"toc-text\">俯卧撑</span></a></li><li class=\"toc-item toc-level-1\"><a class=\"toc-link\" href=\"#%E5%BC%80%E5%90%88%E8%B7%B3\"><span class=\"toc-text\">开合跳</span></a><ol class=\"toc-child\"><li class=\"toc-item toc-level-2\"><a class=\"toc-link\" href=\"#%E7%99%BB%E5%B1%B1%E8%80%85\"><span class=\"toc-text\">登山者</span></a></li></ol></li><li class=\"toc-item toc-level-1\"><a class=\"toc-link\" href=\"#%E6%B3%A2%E6%AF%94%E8%B7%B3\"><span class=\"toc-text\">波比跳</span></a></li></ol>","author":{"name":"uuxia","slug":"blog-author","avatar":"/medias/avatar.jpg","link":"/","description":"一位正在重塑知识的技术人 <br /> @ <b>欢迎光临</b>","socials":{"github":"https://github.com/xxl6097","twitter":"","stackoverflow":"","wechat":"","qq":"","weibo":"","zhihu":"","csdn":"","juejin":"","customs":{"baidu":{"icon":"https://himg.bdimg.com/sys/portrait/item/public.1.868e95ea.DjJabcwawzIP0jmepO6KfQ.jpg","link":"https://www.baidu.com/my/index"}}}},"mapped":true,"prev_post":{"title":"国庆长假新疆旅行-北疆环游","uid":"db83931b422b43af6580741bf7713026","slug":"xj-north-circle","date":"2019-10-21T08:57:49.000Z","updated":"2022-02-22T07:14:54.000Z","comments":true,"path":"api/articles/xj-north-circle.json","cover":[],"text":"行程速览 注意事项： 日照强烈日夜温差大，做好防晒带好冲锋衣或羽绒服（特别是喀纳斯地区，观鱼亭山顶大风变幻莫测）; 新疆各景点之间距离较远，基本每天换酒店，一次性生活用品带足（建议内裤袜子毛巾也最好买一次性）; 自驾比较随性，建议当天订隔天酒店即可（最好订景区附近城镇，性价比高又...","link":"","photos":[],"count_time":{"symbolsCount":"3k","symbolsTime":"3 mins."},"categories":[{"name":"旅行","slug":"旅行","count":1,"path":"api/categories/旅行.json"}],"tags":[{"name":"新疆","slug":"新疆","count":1,"path":"api/tags/新疆.json"},{"name":"北疆","slug":"北疆","count":1,"path":"api/tags/北疆.json"}],"author":{"name":"uuxia","slug":"blog-author","avatar":"/medias/avatar.jpg","link":"/","description":"一位正在重塑知识的技术人 <br /> @ <b>欢迎光临</b>","socials":{"github":"https://github.com/xxl6097","twitter":"","stackoverflow":"","wechat":"","qq":"","weibo":"","zhihu":"","csdn":"","juejin":"","customs":{"baidu":{"icon":"https://himg.bdimg.com/sys/portrait/item/public.1.868e95ea.DjJabcwawzIP0jmepO6KfQ.jpg","link":"https://www.baidu.com/my/index"}}}}},"next_post":{"title":"树莓派3B(Raspberry 3B)搭建HomeAssistant","uid":"d9f74a797f08df0b0fe9d63aaea4208d","slug":"homeassistant","date":"2018-05-02T04:14:57.000Z","updated":"2022-02-18T10:17:37.000Z","comments":true,"path":"api/articles/homeassistant.json","cover":[],"text":"Home Assistant 是一款基于 Python 的智能家居开源系统，支持众多品牌的智能家居设备，可以轻松实现设备的语音控制、自动化等。本文档全站内容基于 Home Assistant 官方网站 本地化而成，具有以下特点： 整合『组件』与『文档』页，采用更直观清晰、符合中文...","link":"","photos":[],"count_time":{"symbolsCount":"5k","symbolsTime":"5 mins."},"categories":[{"name":"IoT","slug":"IoT","count":4,"path":"api/categories/IoT.json"}],"tags":[{"name":"IoT","slug":"IoT","count":1,"path":"api/tags/IoT.json"},{"name":"HomeAssistant","slug":"HomeAssistant","count":1,"path":"api/tags/HomeAssistant.json"}],"author":{"name":"uuxia","slug":"blog-author","avatar":"/medias/avatar.jpg","link":"/","description":"一位正在重塑知识的技术人 <br /> @ <b>欢迎光临</b>","socials":{"github":"https://github.com/xxl6097","twitter":"","stackoverflow":"","wechat":"","qq":"","weibo":"","zhihu":"","csdn":"","juejin":"","customs":{"baidu":{"icon":"https://himg.bdimg.com/sys/portrait/item/public.1.868e95ea.DjJabcwawzIP0jmepO6KfQ.jpg","link":"https://www.baidu.com/my/index"}}}}}}