{"name":"驱蚊  life","slug":"驱蚊-life","count":1,"postlist":[{"title":"教你几招，蚊子一个夏天不敢进你的房间！！","uid":"abc951d0c14e2bccc2284934d80582aa","slug":"gowaywenzi","date":"2016-05-08T23:58:25.000Z","updated":"2022-02-18T10:17:37.000Z","comments":true,"path":"api/articles/gowaywenzi.json","cover":[],"text":"教你几招，蚊子一个夏天不敢进你的房间！！ 前言“多蚊季节来了，谁都不叮偏偏就来叮你？嗡嗡吵得睡不着？怕宝宝被感染？下面教教大家一些驱蚊小窍门！！ 方法一： 用空酒瓶装上糖水或啤酒放在阴暗处，蚊子闻到甜味就会往瓶子里钻，会被啤酒或糖水黏住致死。 方法二：沸过的醋用碟装，放到房间里不...","link":"","photos":[],"count_time":{"symbolsCount":823,"symbolsTime":"1 mins."},"categories":[{"name":"生活","slug":"生活","count":4,"path":"api/categories/生活.json"}],"tags":[{"name":"驱蚊  life","slug":"驱蚊-life","count":1,"path":"api/tags/驱蚊-life.json"}],"author":{"name":"Aurora","slug":"blog-author","avatar":"https://img-blog.csdnimg.cn/20210313122054101.png","link":"/","description":"","socials":{"github":"","twitter":"","stackoverflow":"","wechat":"","qq":"","weibo":"","zhihu":"","csdn":"","juejin":"","customs":{}}}}]}